crypto_com_agent_plugin_discord/__init__.py
crypto_com_agent_plugin_discord/main.py
cryptocom_agent_plugin_discord-1.0.2.dist-info/METADATA
cryptocom_agent_plugin_discord-1.0.2.dist-info/WHEEL
cryptocom_agent_plugin_discord-1.0.2.dist-info/entry_points.txt
cryptocom_agent_plugin_discord-1.0.2.dist-info/RECORD
